src/video_mcp_server.py
video_mcp-0.1.0.dist-info/METADATA
video_mcp-0.1.0.dist-info/WHEEL
video_mcp-0.1.0.dist-info/entry_points.txt
video_mcp-0.1.0.dist-info/RECORD
