Metadata-Version: 2.4
Name: video-mcp
Version: 0.1.0
Summary: Video information search MCP server
Project-URL: Repository, https://github.com/yourusername/video-mcp
Author: Cline
License-Expression: MIT
Classifier: Development Status :: 4 - Beta
Classifier: Environment :: Console
Classifier: Programming Language :: Python :: 3
Classifier: Programming Language :: Python :: 3.12
Requires-Python: >=3.12
Requires-Dist: mcp[cli]>=1.6.0
Requires-Dist: python-dotenv>=1.0.0
Requires-Dist: tmdbv3api>=1.9.0
